sabaka/__init__.py
sabaka/base.py
sabaka/configuration.py
sabaka/errors.py
sabaka-0.1.0.dist-info/LICENSE
sabaka-0.1.0.dist-info/WHEEL
sabaka-0.1.0.dist-info/METADATA
sabaka-0.1.0.dist-info/RECORD
