Metadata-Version: 2.1
Name: sabaka
Version: 0.1.0
Summary: flexible python error messaging
Home-page: https://github.com/WithPrecedent/sabaka
License: Apache-2.0
Author: Corey Rayburn Yung
Author-email: coreyrayburnyung@gmail.com
Requires-Python: >=3.9,<4.0
Classifier: License :: OSI Approved :: Apache Software License
Classifier: Programming Language :: Python :: 3
Classifier: Programming Language :: Python :: 3.9
Classifier: Programming Language :: Python :: 3.10
Project-URL: Repository, https://github.com/WithPrecedent/sabaka
